setup.py
punc/__init__.py
punc/collect.py
punc/config.py
punc/main.py
punc/model.py
punc/parser.py
punc/rc_hg.py
punc/ruleset_factory.py
punc/util.py
punc.egg-info/PKG-INFO
punc.egg-info/SOURCES.txt
punc.egg-info/dependency_links.txt
punc.egg-info/entry_points.txt
punc.egg-info/requires.txt
punc.egg-info/top_level.txt
punc.egg-info/zip-safe
punc/rulesets/__init__.py
punc/rulesets/adva_fsp.py
punc/rulesets/arbor.py
punc/rulesets/cisco.py
punc/rulesets/dasan_nos.py
punc/rulesets/juniper.py
punc/rulesets/netscreen.py
punc/rulesets/telco.py
punc/rulesets/timetra.py