Metadata-Version: 1.0
Name: punc
Version: 0.2
Summary: Pick Up Network (Device) Configuration
Home-page: http://code.google.com/p/punc/
Author: Andrew Fort
Author-email: notch-dev@googlegroups.com
License: http://www.apache.org/licenses/LICENSE-2.0
Platform: UNKNOWN
Classifier: Development Status :: 2 - Pre-Alpha
Classifier: Environment :: Console
Classifier: Intended Audience :: System Administrators
Classifier: License :: OSI Approved :: Apache Software License
Classifier: Operating System :: POSIX
Classifier: Programming Language :: Python :: 2.6
Classifier: Topic :: System :: Networking :: Monitoring
Classifier: Topic :: System :: Systems Administration
